contextaware_processors/__init__.py
contextaware_processors/conf.py
contextaware_processors/middleware.py
contextaware_processors/response.py
contextaware_processors/tests/__init__.py
contextaware_processors/tests/test_drf.py
contextaware_processors/tests/test_middleware.py
contextaware_processors/tests/test_response.py
django_contextaware_processors-0.1.1.dist-info/DESCRIPTION.rst
django_contextaware_processors-0.1.1.dist-info/LICENSE.txt
django_contextaware_processors-0.1.1.dist-info/METADATA
django_contextaware_processors-0.1.1.dist-info/RECORD
django_contextaware_processors-0.1.1.dist-info/WHEEL
django_contextaware_processors-0.1.1.dist-info/metadata.json
django_contextaware_processors-0.1.1.dist-info/top_level.txt
