Metadata-Version: 2.0
Name: django-contextaware-processors
Version: 0.1.1
Summary: Before a Django TemplateResponse is rendered, modify the context data in-place with context-processor like functionality 
Home-page: https://www.github.com/kezabelle/django-contextaware-processors/
Author: Keryn Knight
Author-email: django-contextaware-processors@kerynknight.com
License: BSD License
Keywords: django contextaware_processors template context
Platform: UNKNOWN
Classifier: Development Status :: 3 - Alpha
Classifier: Intended Audience :: Developers
Classifier: License :: OSI Approved :: BSD License
Classifier: Natural Language :: English
Classifier: Programming Language :: Python :: 2
Classifier: Programming Language :: Python :: 2.7
Classifier: Programming Language :: Python :: 3
Classifier: Programming Language :: Python :: 3.3
Classifier: Programming Language :: Python :: 3.4
Classifier: Programming Language :: Python :: 3.5
Classifier: Framework :: Django
Classifier: Framework :: Django :: 1.10
Classifier: Framework :: Django :: 1.8
Classifier: Framework :: Django :: 1.9
Requires-Dist: Django (>=1.8)
